bybit_backtest/__init__.py
bybit_backtest/bybit_backtest.py
bybit_backtest-0.1.5.dist-info/LICENSE.txt
bybit_backtest-0.1.5.dist-info/METADATA
bybit_backtest-0.1.5.dist-info/WHEEL
bybit_backtest-0.1.5.dist-info/top_level.txt
bybit_backtest-0.1.5.dist-info/RECORD
