Metadata-Version: 2.1
Name: bybit-backtest
Version: 0.1.5
Summary: bybit-backtest is a python library         for backtest with bybit fx trade on Python 3.7 and above.
Home-page: https://github.com/10mohi6/bybit-backtest-python
Author: 10mohi6
Author-email: 10.mohi.6.y@gmail.com
License: MIT
Keywords: bybit trade python backtest fx usdt usd btc
Platform: UNKNOWN
Classifier: Development Status :: 4 - Beta
Classifier: Programming Language :: Python
Classifier: Programming Language :: Python :: 3
Classifier: Programming Language :: Python :: 3.7
Classifier: Programming Language :: Python :: 3.8
Classifier: Programming Language :: Python :: 3.9
Classifier: Intended Audience :: Developers
Classifier: Intended Audience :: Financial and Insurance Industry
Classifier: Operating System :: OS Independent
Classifier: Topic :: Office/Business :: Financial :: Investment
Classifier: License :: OSI Approved :: MIT License
Requires-Python: >=3.7.0
Requires-Dist: requests
Requires-Dist: numpy
Requires-Dist: pandas
Requires-Dist: matplotlib
Requires-Dist: beautifulsoup4
Requires-Dist: SQLAlchemy
Requires-Dist: lxml
